statez/__init__.py
statez/core.py
statez/utils.py
statez-0.3.4.dist-info/COPYING
statez-0.3.4.dist-info/WHEEL
statez-0.3.4.dist-info/METADATA
statez-0.3.4.dist-info/RECORD
